{
    "Eye": [200, 200, 1000],
    "Lights": [
        {
            "position": [-200, 600, 1500],
            "color": [1.0, 1.0, 1.0]
        }
    ],
    "Objects": [
        {
            "type": "quad",
            "comment": "Green quad",
            "vertex2": [200, 230, 100],
	    "vertex1": [40, 200, 100],
	    "vertex3": [400, 370, 100],
	    "vertex4": [400, 200, 100],
            "material":
            {
                "color": [0.0, 1.0, 0.0],
                "ka": 0.2,
                "kd": 0.7,
                "ks": 0.5,
                "n": 64
            }
        }
    ]
}
